light_the_torch/__init__.py
light_the_torch/__main__.py
light_the_torch/_cb.py
light_the_torch/_cli.py
light_the_torch/_patch.py
light_the_torch/_utils.py
light_the_torch/_version.py
light_the_torch-0.8.0.dist-info/LICENSE
light_the_torch-0.8.0.dist-info/METADATA
light_the_torch-0.8.0.dist-info/WHEEL
light_the_torch-0.8.0.dist-info/entry_points.txt
light_the_torch-0.8.0.dist-info/top_level.txt
light_the_torch-0.8.0.dist-info/RECORD
