Metadata-Version: 2.1
Name: light_the_torch
Version: 0.8.0
Summary: Install PyTorch distributions with computation backend auto-detection
Author-email: Philip Meier <github.pmeier@posteo.de>
License: BSD-3-Clause
Project-URL: Tracker, https://github.com/pmeier/light-the-torch/issues
Project-URL: Source, https://github.com/pmeier/light-the-torch
Keywords: pytorch,cuda,pip,install
Classifier: Development Status :: 4 - Beta
Classifier: Environment :: Console
Classifier: Environment :: GPU :: NVIDIA CUDA
Classifier: Intended Audience :: Developers
Classifier: License :: OSI Approved :: BSD License
Classifier: Programming Language :: Python :: 3.9
Classifier: Programming Language :: Python :: 3.10
Classifier: Programming Language :: Python :: 3.11
Classifier: Programming Language :: Python :: 3.12
Classifier: Topic :: System :: Installation/Setup
Classifier: Topic :: Utilities
Requires-Python: >=3.9
License-File: LICENSE
Requires-Dist: pip<24.4,>=22.3
